git_nb/__init__.py
git_nb/config.py
git_nb-0.1.4.dist-info/METADATA
git_nb-0.1.4.dist-info/WHEEL
git_nb-0.1.4.dist-info/top_level.txt
git_nb-0.1.4.dist-info/RECORD
